nlmaps_tools/__init__.py
nlmaps_tools/answer_mrl.py
nlmaps_tools/answer_overpass.py
nlmaps_tools/data/additional_tags.json
nlmaps_tools/data/dropped_keys.txt
nlmaps_tools/data/most_common_tags.json
nlmaps_tools/data/open_keys.txt
nlmaps_tools/data/special_phrases.txt
nlmaps_tools/features_to_overpass.py
nlmaps_tools/fix_nlmaps_v2.py
nlmaps_tools/generate_mrl.py
nlmaps_tools/generate_nl.py
nlmaps_tools/make_tag_dict.py
nlmaps_tools/mrl/README.md
nlmaps_tools/mrl/__init__.py
nlmaps_tools/mrl/cfgs/nlmaps
nlmaps_tools/mrl/functionalise.py
nlmaps_tools/mrl/linearise.py
nlmaps_tools/mrl/local_io.py
nlmaps_tools/mrl/mrl.py
nlmaps_tools/mrl/test.py
nlmaps_tools/mrl_templates/around_query.jinja2
nlmaps_tools/mrl_templates/base_query.jinja2
nlmaps_tools/mrl_templates/dist.jinja2
nlmaps_tools/mrl_templates/in_query.jinja2
nlmaps_tools/nl_queries.txt
nlmaps_tools/nl_templates/around_query/count_does_have.jinja2
nlmaps_tools/nl_templates/around_query/count_how_many_does_have.jinja2
nlmaps_tools/nl_templates/around_query/count_in_how_many.jinja2
nlmaps_tools/nl_templates/around_query/latlong_in_where.jinja2
nlmaps_tools/nl_templates/around_query/least1_does_have.jinja2
nlmaps_tools/nl_templates/around_query/least1_in_are_there.jinja2
nlmaps_tools/nl_templates/around_query/name_in_what.jinja2
nlmaps_tools/nl_templates/around_query/name_what_does_have.jinja2
nlmaps_tools/nl_templates/around_query/name_what_in_separate.jinja2
nlmaps_tools/nl_templates/around_query/opening-hours_in_give.jinja2
nlmaps_tools/nl_templates/around_query/opening-hours_in_when_open.jinja2
nlmaps_tools/nl_templates/around_query/opening-hours_in_when_visit.jinja2
nlmaps_tools/nl_templates/closest_around_query/latlong_give.jinja2
nlmaps_tools/nl_templates/closest_around_query/latlong_where.jinja2
nlmaps_tools/nl_templates/closest_around_query/name_name.jinja2
nlmaps_tools/nl_templates/closest_around_query/name_what.jinja2
nlmaps_tools/nl_templates/closest_around_query/opening-hours_give.jinja2
nlmaps_tools-0.0.3.dist-info/LICENSE
nlmaps_tools-0.0.3.dist-info/METADATA
nlmaps_tools-0.0.3.dist-info/WHEEL
nlmaps_tools-0.0.3.dist-info/RECORD
